{
	"condition": "minecraft:alternative",
	"terms": [
		{
			"condition": "minecraft:location_check",
			"predicate": {
				"block": {
					"nbt": "{Items:[{Slot:7b,tag:{id:'cpp:wing_of_sky'},Count:1b}]}"
				}
			}
		},
		{
			"condition": "minecraft:location_check",
			"predicate": {
				"block": {
					"nbt": "{Items:[{Slot:7b,tag:{id:'cpp:heart_of_crystal'},Count:1b}]}"
				}
			}
		},
		{
			"condition": "minecraft:location_check",
			"predicate": {
				"block": {
					"nbt": "{Items:[{Slot:7b,tag:{id:'cpp:limb_of_ridge'},Count:1b}]}"
				}
			}
		},
		{
			"condition": "minecraft:location_check",
			"predicate": {
				"block": {
					"nbt": "{Items:[{Slot:7b,tag:{id:'cpp:soul_of_dirt'},Count:1b}]}"
				}
			}
		},
		{
			"condition": "minecraft:location_check",
			"predicate": {
				"block": {
					"nbt": "{Items:[{Slot:7b,tag:{id:'cpp:certification_of_earth'},Count:1b}]}"
				}
			}
		},
		{
			"condition": "minecraft:location_check",
			"predicate": {
				"block": {
					"nbt": "{Items:[{Slot:7b,tag:{id:'cpp:nova_of_fire'},Count:1b}]}"
				}
			}
		},
		{
			"condition": "minecraft:location_check",
			"predicate": {
				"block": {
					"nbt": "{Items:[{Slot:7b,tag:{id:'cpp:spirit_of_life'},Count:1b}]}"
				}
			}
		}
	]
}